twnews/__init__.py
twnews/__main__.py
twnews/common.py
twnews/search.py
twnews/soup.py
twnews/__pycache__/__init__.cpython-37.pyc
twnews/__pycache__/common.cpython-37.pyc
twnews/__pycache__/search.cpython-37.pyc
twnews/__pycache__/soup.cpython-37.pyc
twnews/conf/logging.ini
twnews/conf/news-soup.json
twnews/conf/usage.txt
twnews/samples/appledaily.html.xz
twnews/samples/chinatimes.html.xz
twnews/samples/cna.html.xz
twnews/samples/ettoday.html.xz
twnews/samples/ltn.html.xz
twnews/samples/setn.html.xz
twnews/samples/udn.html.xz
twnews/tests/__init__.py
twnews/tests/__pycache__/__init__.cpython-37.pyc
twnews/tests/search/__init__.py
twnews/tests/search/test_search_appledaily.py
twnews/tests/search/test_search_cna.py
twnews/tests/search/test_search_ettoday.py
twnews/tests/search/test_search_ltn.py
twnews/tests/search/test_search_setn.py
twnews/tests/search/test_search_udn.py
twnews/tests/search/__pycache__/__init__.cpython-37.pyc
twnews/tests/search/__pycache__/test_search_appledaily.cpython-37.pyc
twnews/tests/search/__pycache__/test_search_cna.cpython-37.pyc
twnews/tests/search/__pycache__/test_search_ettoday.cpython-37.pyc
twnews/tests/search/__pycache__/test_search_ltn.cpython-37.pyc
twnews/tests/search/__pycache__/test_search_setn.cpython-37.pyc
twnews/tests/search/__pycache__/test_search_udn.cpython-37.pyc
twnews/tests/soup/__init__.py
twnews/tests/soup/test_soup_appledaily.py
twnews/tests/soup/test_soup_chinatimes.py
twnews/tests/soup/test_soup_cna.py
twnews/tests/soup/test_soup_common.py
twnews/tests/soup/test_soup_ettoday.py
twnews/tests/soup/test_soup_ltn.py
twnews/tests/soup/test_soup_setn.py
twnews/tests/soup/test_soup_udn.py
twnews/tests/soup/__pycache__/__init__.cpython-37.pyc
twnews/tests/soup/__pycache__/test_soup_appledaily.cpython-37.pyc
twnews/tests/soup/__pycache__/test_soup_chinatimes.cpython-37.pyc
twnews/tests/soup/__pycache__/test_soup_cna.cpython-37.pyc
twnews/tests/soup/__pycache__/test_soup_common.cpython-37.pyc
twnews-0.3.3.dist-info/LICENSE
twnews-0.3.3.dist-info/METADATA
twnews-0.3.3.dist-info/WHEEL
twnews-0.3.3.dist-info/top_level.txt
twnews-0.3.3.dist-info/RECORD
