Metadata-Version: 2.1
Name: twnews
Version: 0.3.3
Summary: To tear down news web pages in Taiwan.
Home-page: https://github.com/virus-warnning/twnews
Author: Raymond Wu
License: MIT
Platform: UNKNOWN
Requires-Python: >=3.5
Requires-Dist: beautifulsoup4 (>=4.7.1)
Requires-Dist: busm (>=0.8.0)
Requires-Dist: lxml (>=4.3.3)
Requires-Dist: requests (>=2.21.0)
Requires-Dist: pandas (>=0.24.2)
